bmiiiiii/bmi_test.py
bmiiiiii-0.0.0.4.dist-info/METADATA
bmiiiiii-0.0.0.4.dist-info/WHEEL
bmiiiiii-0.0.0.4.dist-info/top_level.txt
bmiiiiii-0.0.0.4.dist-info/RECORD
