Metadata-Version: 2.1
Name: bmiiiiii
Version: 0.0.0.4
Summary: My First Test Package
Home-page: https://www.naver.com/
Author: fghj55
Author-email: kangth334@gmail.com
License: MIT
Requires-Python: >=3
